simple_latex_generator/__init__.py
simple_latex_generator/example.py
simple_latex_generator/meme.png
simple_latex_generator/simple_latex_generator.py
simple_latex_generator-0.1.1.dist-info/METADATA
simple_latex_generator-0.1.1.dist-info/WHEEL
simple_latex_generator-0.1.1.dist-info/top_level.txt
simple_latex_generator-0.1.1.dist-info/RECORD
