Metadata-Version: 2.4
Name: simple-latex-generator
Version: 0.1.1
Summary: Генератор LaTeX-кода для таблиц и изображений
Author: Mikhail Nikolaev
Keywords: latex,meme
Classifier: Programming Language :: Python :: 3
Requires-Python: >=3.7
